gitapi_it/__init__.py
gitapi_it/test.py
gitapi_it-0.5.1.dist-info/LICENSE
gitapi_it-0.5.1.dist-info/METADATA
gitapi_it-0.5.1.dist-info/WHEEL
gitapi_it-0.5.1.dist-info/top_level.txt
gitapi_it-0.5.1.dist-info/zip-safe
gitapi_it-0.5.1.dist-info/RECORD
