Metadata-Version: 2.1
Name: gitapi_it
Version: 0.5.1
Summary: For all of your console needs!
Home-page: https://github.com/GitAPI-it/GitAPI.it-Pythony
Author: darkdarcool30
Author-email: darkdarcool@gmail.com
License: GNU General Public License v3 (GPLv3)
Platform: UNKNOWN
Classifier: Programming Language :: Python :: 3
Classifier: License :: OSI Approved :: GNU General Public License v3 (GPLv3)
Classifier: Operating System :: OS Independent
Requires-Python: >=3.0
License-File: LICENSE
